mingdaoyun_sdk/MingdaoOrg.py
mingdaoyun_sdk/MingdaoYun.py
mingdaoyun_sdk/__init__.py
mingdaoyun_sdk/common.py
mingdaoyun_sdk-0.0.16.dist-info/METADATA
mingdaoyun_sdk-0.0.16.dist-info/WHEEL
mingdaoyun_sdk-0.0.16.dist-info/top_level.txt
mingdaoyun_sdk-0.0.16.dist-info/RECORD
