Metadata-Version: 2.4
Name: mingdaoyun_sdk
Version: 0.0.16
Summary: 针对mingdaoyun的API封装的Python-SDK包
Home-page: https://github.com/ghostlitao/mingdaoyun-python-sdk
Author: Todd
Author-email: ghostlitao@gmail.com
Classifier: Programming Language :: Python :: 3
Classifier: License :: OSI Approved :: MIT License
Classifier: Operating System :: OS Independent
Dynamic: author
Dynamic: author-email
Dynamic: classifier
Dynamic: description
Dynamic: description-content-type
Dynamic: home-page
Dynamic: summary
